flexi_formatter/__init__.py
flexi_formatter/reformat_flexiplex_tags.py
flexi_formatter-1.0.1.dist-info/LICENSE
flexi_formatter-1.0.1.dist-info/METADATA
flexi_formatter-1.0.1.dist-info/WHEEL
flexi_formatter-1.0.1.dist-info/entry_points.txt
flexi_formatter-1.0.1.dist-info/top_level.txt
flexi_formatter-1.0.1.dist-info/RECORD
