Metadata-Version: 2.1
Name: flexi_formatter
Version: 1.0.1
Summary: Moving flexiplex barcode and UMI to bam tags
Author: Luuk Harbers
Author-email: luuk.harbers@kuleuven.be
License: MIT
Classifier: Programming Language :: Python :: 3
Classifier: License :: OSI Approved :: MIT License
Classifier: Operating System :: OS Independent
Classifier: Intended Audience :: Science/Research
Classifier: Programming Language :: Python
Requires-Python: >=3.7
License-File: LICENSE
Requires-Dist: typer==0.12.3
Requires-Dist: simplesam==0.1.4.1
